portacode/README.md
portacode/__init__.py
portacode/__main__.py
portacode/_version.py
portacode/cli.py
portacode/data.py
portacode/keypair.py
portacode/logging_categories.py
portacode/pairing.py
portacode/service.py
portacode/connection/README.md
portacode/connection/__init__.py
portacode/connection/client.py
portacode/connection/multiplex.py
portacode/connection/terminal.py
portacode/connection/handlers/README.md
portacode/connection/handlers/WEBSOCKET_PROTOCOL.md
portacode/connection/handlers/__init__.py
portacode/connection/handlers/base.py
portacode/connection/handlers/chunked_content.py
portacode/connection/handlers/diff_handlers.py
portacode/connection/handlers/file_handlers.py
portacode/connection/handlers/project_aware_file_handlers.py
portacode/connection/handlers/project_state_handlers.py
portacode/connection/handlers/proxmox_infra.py
portacode/connection/handlers/registry.py
portacode/connection/handlers/session.py
portacode/connection/handlers/system_handlers.py
portacode/connection/handlers/tab_factory.py
portacode/connection/handlers/terminal_handlers.py
portacode/connection/handlers/test_proxmox_infra.py
portacode/connection/handlers/update_handler.py
portacode/connection/handlers/project_state/README.md
portacode/connection/handlers/project_state/__init__.py
portacode/connection/handlers/project_state/file_system_watcher.py
portacode/connection/handlers/project_state/git_manager.py
portacode/connection/handlers/project_state/handlers.py
portacode/connection/handlers/project_state/manager.py
portacode/connection/handlers/project_state/models.py
portacode/connection/handlers/project_state/utils.py
portacode/link_capture/__init__.py
portacode/link_capture/__pycache__/__init__.cpython-311.pyc
portacode/link_capture/bin/elinks
portacode/link_capture/bin/gio-open
portacode/link_capture/bin/gnome-open
portacode/link_capture/bin/gvfs-open
portacode/link_capture/bin/kde-open
portacode/link_capture/bin/kfmclient
portacode/link_capture/bin/link_capture_exec.sh
portacode-1.4.18.dist-info/licenses/LICENSE
portacode-1.4.18.dist-info/METADATA
portacode-1.4.18.dist-info/WHEEL
portacode-1.4.18.dist-info/entry_points.txt
portacode-1.4.18.dist-info/top_level.txt
portacode-1.4.18.dist-info/RECORD
