Metadata-Version: 2.4
Name: portacode
Version: 1.4.18
Summary: Portacode CLI client and SDK
Home-page: https://github.com/portacode/portacode
Author: Meena Erian
Author-email: hi@menas.pro
Classifier: Programming Language :: Python :: 3
Classifier: Programming Language :: Python :: 3.8
Classifier: Programming Language :: Python :: 3.9
Classifier: Programming Language :: Python :: 3.10
Classifier: Programming Language :: Python :: 3.11
Classifier: License :: OSI Approved :: MIT License
Classifier: Operating System :: OS Independent
Requires-Python: >=3.8
License-File: LICENSE
Requires-Dist: click>=8.0
Requires-Dist: platformdirs>=3.0
Requires-Dist: cryptography>=41.0
Requires-Dist: websockets>=12.0
Requires-Dist: pyperclip>=1.8
Requires-Dist: psutil>=5.9
Requires-Dist: pyte>=0.8
Requires-Dist: pywinpty>=2.0; platform_system == "Windows"
Requires-Dist: GitPython>=3.1.45
Requires-Dist: watchdog>=3.0
Requires-Dist: diff-match-patch>=20230430
Requires-Dist: Pygments>=2.14.0
Requires-Dist: ntplib>=0.4.0
Requires-Dist: importlib_resources>=6.0
Provides-Extra: dev
Requires-Dist: black; extra == "dev"
Requires-Dist: flake8; extra == "dev"
Requires-Dist: pytest; extra == "dev"
Dynamic: author
Dynamic: author-email
Dynamic: classifier
Dynamic: description
Dynamic: description-content-type
Dynamic: home-page
Dynamic: license-file
Dynamic: provides-extra
Dynamic: requires-dist
Dynamic: requires-python
Dynamic: summary
